MANIFEST.in
README.rst
setup.py
docs/HISTORY.txt
docs/LICENSE.GPL
docs/LICENSE.txt
docs/screenshot.png
ftw/__init__.py
ftw.activity.egg-info/PKG-INFO
ftw.activity.egg-info/SOURCES.txt
ftw.activity.egg-info/dependency_links.txt
ftw.activity.egg-info/entry_points.txt
ftw.activity.egg-info/namespace_packages.txt
ftw.activity.egg-info/not-zip-safe
ftw.activity.egg-info/requires.txt
ftw.activity.egg-info/top_level.txt
ftw/activity/__init__.py
ftw/activity/configure.zcml
ftw/activity/events.py
ftw/activity/filters.py
ftw/activity/hooks.py
ftw/activity/interfaces.py
ftw/activity/resources.zcml
ftw/activity/subscribers.py
ftw/activity/testing.py
ftw/activity/utils.py
ftw/activity/Extensions/install.py
ftw/activity/browser/__init__.py
ftw/activity/browser/activity.py
ftw/activity/browser/configure.zcml
ftw/activity/browser/local.py
ftw/activity/browser/renderer.py
ftw/activity/browser/tab.py
ftw/activity/browser/templates/activity.pt
ftw/activity/browser/templates/activity_macros.pt
ftw/activity/browser/templates/activity_raw.pt
ftw/activity/browser/templates/comment.pt
ftw/activity/browser/templates/default.pt
ftw/activity/browser/templates/events.pt
ftw/activity/catalog/__init__.py
ftw/activity/catalog/configure.zcml
ftw/activity/catalog/factory.py
ftw/activity/catalog/locator.py
ftw/activity/catalog/record.py
ftw/activity/locales/ftw.activity-manual.pot
ftw/activity/locales/ftw.activity.pot
ftw/activity/locales/ftw.tabbedview.pot
ftw/activity/locales/de/LC_MESSAGES/ftw.activity.po
ftw/activity/locales/de/LC_MESSAGES/ftw.tabbedview.po
ftw/activity/locales/en/LC_MESSAGES/ftw.activity.po
ftw/activity/locales/en/LC_MESSAGES/ftw.tabbedview.po
ftw/activity/portlets/__init__.py
ftw/activity/portlets/activity_portlet.py
ftw/activity/portlets/configure.zcml
ftw/activity/portlets/templates/activity_portlet.pt
ftw/activity/profiles/base/metadata.xml
ftw/activity/profiles/base/portlets.xml
ftw/activity/profiles/plone4/jsregistry.xml
ftw/activity/profiles/plone4/metadata.xml
ftw/activity/profiles/plone5/metadata.xml
ftw/activity/profiles/plone5/registry.xml
ftw/activity/profiles/uninstall/jsregistry.xml
ftw/activity/profiles/uninstall/portlets.xml
ftw/activity/profiles/uninstall_plone5/portlets.xml
ftw/activity/profiles/uninstall_plone5/registry.xml
