Metadata-Version: 2.1
Name: ftw.activity
Version: 2.5.2
Summary: An activity feed for Plone.
Home-page: https://github.com/4teamwork/ftw.activity
Author: 4teamwork AG
Author-email: mailto:info@4teamwork.ch
License: GPL2
Keywords: ftw activity feed
Platform: UNKNOWN
Classifier: Framework :: Plone
Classifier: Framework :: Plone :: 4.3
Classifier: Framework :: Plone :: 5.1
Classifier: Intended Audience :: Developers
Classifier: Topic :: Software Development :: Libraries :: Python Modules
Provides-Extra: tests
Provides-Extra: plone4_test
